appknox/__init__.py
appknox/cli.py
appknox/client.py
appknox/exceptions.py
appknox/mapper.py
appknox/version.py
appknox-4.3.0.dist-info/LICENSE
appknox-4.3.0.dist-info/METADATA
appknox-4.3.0.dist-info/WHEEL
appknox-4.3.0.dist-info/entry_points.txt
appknox-4.3.0.dist-info/top_level.txt
appknox-4.3.0.dist-info/RECORD
