Metadata-Version: 2.1
Name: appknox
Version: 4.3.0
Summary: Command-line interface & Python wrapper for the Appknox API
Home-page: https://github.com/appknox/appknox-python
Author: Appknox
Author-email: engineering@appknox.com
License: MIT
Keywords: appknox xysec rest api wrapper cli mobile security
Platform: UNKNOWN
Classifier: Development Status :: 5 - Production/Stable
Classifier: Intended Audience :: Developers
Classifier: Topic :: Software Development :: Build Tools
Classifier: License :: OSI Approved :: MIT License
Classifier: Programming Language :: Python :: 3
Classifier: Programming Language :: Python :: 3.5
License-File: LICENSE
Requires-Dist: click (>=7)
Requires-Dist: requests (>=2.20)
Requires-Dist: tabulate (>=0.8)
Requires-Dist: black (==22.12.0)
Requires-Dist: flake8-bugbear (==23.1.17)
Requires-Dist: flake8-isort (==6.0.0)
Provides-Extra: dev
Provides-Extra: test
